agenttrace/__init__.py
agenttrace/agenttrace.py
agenttrace/cli.py
agenttrace/py.typed
agenttrace-0.1.2.dist-info/licenses/LICENSE
agenttrace-0.1.2.dist-info/METADATA
agenttrace-0.1.2.dist-info/WHEEL
agenttrace-0.1.2.dist-info/entry_points.txt
agenttrace-0.1.2.dist-info/top_level.txt
agenttrace-0.1.2.dist-info/RECORD
