Metadata-Version: 2.4
Name: agenttrace
Version: 0.1.2
Summary: A lightweight and hackable tracing/evaluation framework for AI agents and language models
Home-page: https://github.com/tensorstax/agenttrace
Author: TensorStax
Author-email: TensorStax <info@tensorstax.com>
License: MIT License
Project-URL: Homepage, https://github.com/tensorstax/agenttrace
Project-URL: Issues, https://github.com/tensorstax/agenttrace/issues
Classifier: Development Status :: 3 - Alpha
Classifier: Intended Audience :: Developers
Classifier: License :: OSI Approved :: MIT License
Classifier: Programming Language :: Python :: 3
Classifier: Programming Language :: Python :: 3.7
Classifier: Programming Language :: Python :: 3.8
Classifier: Programming Language :: Python :: 3.9
Classifier: Programming Language :: Python :: 3.10
Requires-Python: >=3.7
License-File: LICENSE
Requires-Dist: numpy
Dynamic: license-file
